jupyterlab_logtalk_codemirror_extension/__init__.py
jupyterlab_logtalk_codemirror_extension/_version.py
jupyterlab_logtalk_codemirror_extension/labextension/build_log.json
jupyterlab_logtalk_codemirror_extension/labextension/package.json
jupyterlab_logtalk_codemirror_extension/labextension/static/lib_index_js-webpack_sharing_consume_default_lezer_common.b9f09d75cf3f48139155.js
jupyterlab_logtalk_codemirror_extension/labextension/static/lib_index_js-webpack_sharing_consume_default_lezer_common.b9f09d75cf3f48139155.js.map
jupyterlab_logtalk_codemirror_extension/labextension/static/remoteEntry.3caae9894946e2a94661.js
jupyterlab_logtalk_codemirror_extension/labextension/static/remoteEntry.3caae9894946e2a94661.js.map
jupyterlab_logtalk_codemirror_extension/labextension/static/style.js
jupyterlab_logtalk_codemirror_extension/labextension/static/style_index_js.8c83ef68e6a0aeaf9f16.js
jupyterlab_logtalk_codemirror_extension/labextension/static/style_index_js.8c83ef68e6a0aeaf9f16.js.map
jupyterlab_logtalk_codemirror_extension/labextension/static/vendors-node_modules_codemirror_commands_dist_index_js.e9fc0f3beccfde7ab2ea.js
jupyterlab_logtalk_codemirror_extension/labextension/static/vendors-node_modules_codemirror_commands_dist_index_js.e9fc0f3beccfde7ab2ea.js.map
jupyterlab_logtalk_codemirror_extension-1.3.0.data/data/share/jupyter/labextensions/jupyterlab_logtalk_codemirror_extension/build_log.json
jupyterlab_logtalk_codemirror_extension-1.3.0.data/data/share/jupyter/labextensions/jupyterlab_logtalk_codemirror_extension/package.json
jupyterlab_logtalk_codemirror_extension-1.3.0.data/data/share/jupyter/labextensions/jupyterlab_logtalk_codemirror_extension/static/lib_index_js-webpack_sharing_consume_default_lezer_common.b9f09d75cf3f48139155.js
jupyterlab_logtalk_codemirror_extension-1.3.0.data/data/share/jupyter/labextensions/jupyterlab_logtalk_codemirror_extension/static/lib_index_js-webpack_sharing_consume_default_lezer_common.b9f09d75cf3f48139155.js.map
jupyterlab_logtalk_codemirror_extension-1.3.0.dist-info/METADATA
jupyterlab_logtalk_codemirror_extension-1.3.0.dist-info/WHEEL
jupyterlab_logtalk_codemirror_extension-1.3.0.dist-info/licenses/LICENSE
jupyterlab_logtalk_codemirror_extension-1.3.0.dist-info/RECORD
