Metadata-Version: 2.4
Name: jupyterlab_logtalk_codemirror_extension
Version: 1.3.0
Summary: A JupyterLab extension for Logtalk syntax highlighting.
Project-URL: Homepage, https://github.com/LogtalkDotOrg/jupyterlab-logtalk-codemirror-extension
Project-URL: Repository, https://github.com/LogtalkDotOrg/jupyterlab-logtalk-codemirror-extension.git
Project-URL: Bug Tracker, https://github.com/LogtalkDotOrg/jupyterlab-logtalk-codemirror-extension/issues
Author-email: Paulo Moura <pmoura@logtalk.org>
Maintainer-email: Paulo Moura <pmoura@logtalk.org>
License: BSD 3-Clause License
License-File: LICENSE
Keywords: codemirror,jupyter,jupyterlab,jupyterlab-extension,logtalk,syntax-highlighting
Classifier: Framework :: Jupyter
Classifier: Framework :: Jupyter :: JupyterLab
Classifier: Framework :: Jupyter :: JupyterLab :: 4
Classifier: Framework :: Jupyter :: JupyterLab :: Extensions
Classifier: Framework :: Jupyter :: JupyterLab :: Extensions :: Prebuilt
Classifier: License :: OSI Approved :: BSD License
Classifier: Programming Language :: Python
Classifier: Programming Language :: Python :: 3
Classifier: Programming Language :: Python :: 3.8
Classifier: Programming Language :: Python :: 3.9
Classifier: Programming Language :: Python :: 3.10
Classifier: Programming Language :: Python :: 3.11
Classifier: Programming Language :: Python :: 3.12
Requires-Python: >=3.8
Requires-Dist: jupyterlab<5,>=4.0.0
